[
  {
    "eventType": "VIEW_CLICKED",
    "timestamp": 1661765705733,
    "replacementText": "MY RECYCLING STATS",
    "actionCode": -1,
    "delayTime": 0,
    "canScrollTo": false,
    "elementDescriptors": [
      {
        "className": "com.google.android.material.button.MaterialButton",
        "recyclerViewChildPosition": -1,
        "adapterViewChildPosition": -1,
        "groupViewChildPosition": 3,
        "resourceId": "com.example.homework3:id/showStats",
        "contentDescription": "",
        "text": "MY RECYCLING STATS"
      },
      {
        "className": "androidx.constraintlayout.widget.ConstraintLayout",
        "recyclerViewChildPosition": -1,
        "adapterViewChildPosition": -1,
        "groupViewChildPosition": 0,
        "resourceId": "",
        "contentDescription": "",
        "text": ""
      },
      {
        "className": "androidx.fragment.app.FragmentContainerView",
        "recyclerViewChildPosition": -1,
        "adapterViewChildPosition": -1,
        "groupViewChildPosition": 0,
        "resourceId": "com.example.homework3:id/fragmentContainerView",
        "contentDescription": "",
        "text": ""
      }
    ]
  },
  {
    "eventType": "PRESSED_BACK",
    "timestamp": 1661765713187,
    "actionCode": -1,
    "delayTime": 0,
    "canScrollTo": false,
    "elementDescriptors": []
  },
  {
    "eventType": "VIEW_CLICKED",
    "timestamp": 1661765718046,
    "replacementText": "prizes and guide",
    "actionCode": -1,
    "delayTime": 0,
    "canScrollTo": false,
    "elementDescriptors": [
      {
        "className": "com.google.android.material.button.MaterialButton",
        "recyclerViewChildPosition": -1,
        "adapterViewChildPosition": -1,
        "groupViewChildPosition": 1,
        "resourceId": "com.example.homework3:id/showPrizes",
        "contentDescription": "",
        "text": "prizes and guide"
      },
      {
        "className": "androidx.constraintlayout.widget.ConstraintLayout",
        "recyclerViewChildPosition": -1,
        "adapterViewChildPosition": -1,
        "groupViewChildPosition": 0,
        "resourceId": "",
        "contentDescription": "",
        "text": ""
      },
      {
        "className": "androidx.fragment.app.FragmentContainerView",
        "recyclerViewChildPosition": -1,
        "adapterViewChildPosition": -1,
        "groupViewChildPosition": 0,
        "resourceId": "com.example.homework3:id/fragmentContainerView",
        "contentDescription": "",
        "text": ""
      }
    ]
  },
  {
    "eventType": "PRESSED_BACK",
    "timestamp": 1661765721020,
    "actionCode": -1,
    "delayTime": 0,
    "canScrollTo": false,
    "elementDescriptors": []
  },
  {
    "eventType": "VIEW_CLICKED",
    "timestamp": 1661765722837,
    "replacementText": "how can I recycle?",
    "actionCode": -1,
    "delayTime": 0,
    "canScrollTo": false,
    "elementDescriptors": [
      {
        "className": "com.google.android.material.button.MaterialButton",
        "recyclerViewChildPosition": -1,
        "adapterViewChildPosition": -1,
        "groupViewChildPosition": 4,
        "resourceId": "com.example.homework3:id/whatToRecycle",
        "contentDescription": "",
        "text": "how can I recycle?"
      },
      {
        "className": "androidx.constraintlayout.widget.ConstraintLayout",
        "recyclerViewChildPosition": -1,
        "adapterViewChildPosition": -1,
        "groupViewChildPosition": 0,
        "resourceId": "",
        "contentDescription": "",
        "text": ""
      },
      {
        "className": "androidx.fragment.app.FragmentContainerView",
        "recyclerViewChildPosition": -1,
        "adapterViewChildPosition": -1,
        "groupViewChildPosition": 0,
        "resourceId": "com.example.homework3:id/fragmentContainerView",
        "contentDescription": "",
        "text": ""
      }
    ]
  },
  {
    "eventType": "PRESSED_BACK",
    "timestamp": 1661765726143,
    "actionCode": -1,
    "delayTime": 0,
    "canScrollTo": false,
    "elementDescriptors": []
  },
  {
    "eventType": "VIEW_CLICKED",
    "timestamp": 1661765727322,
    "replacementText": "MY RECYCLING STATS",
    "actionCode": -1,
    "delayTime": 0,
    "canScrollTo": false,
    "elementDescriptors": [
      {
        "className": "com.google.android.material.button.MaterialButton",
        "recyclerViewChildPosition": -1,
        "adapterViewChildPosition": -1,
        "groupViewChildPosition": 3,
        "resourceId": "com.example.homework3:id/showStats",
        "contentDescription": "",
        "text": "MY RECYCLING STATS"
      },
      {
        "className": "androidx.constraintlayout.widget.ConstraintLayout",
        "recyclerViewChildPosition": -1,
        "adapterViewChildPosition": -1,
        "groupViewChildPosition": 0,
        "resourceId": "",
        "contentDescription": "",
        "text": ""
      },
      {
        "className": "androidx.fragment.app.FragmentContainerView",
        "recyclerViewChildPosition": -1,
        "adapterViewChildPosition": -1,
        "groupViewChildPosition": 0,
        "resourceId": "com.example.homework3:id/fragmentContainerView",
        "contentDescription": "",
        "text": ""
      }
    ]
  },
  {
    "eventType": "PRESSED_BACK",
    "timestamp": 1661765730928,
    "actionCode": -1,
    "delayTime": 0,
    "canScrollTo": false,
    "elementDescriptors": []
  },
  {
    "eventType": "VIEW_CLICKED",
    "timestamp": 1661765734797,
    "replacementText": "logout",
    "actionCode": -1,
    "delayTime": 0,
    "canScrollTo": false,
    "elementDescriptors": [
      {
        "className": "com.google.android.material.button.MaterialButton",
        "recyclerViewChildPosition": -1,
        "adapterViewChildPosition": -1,
        "groupViewChildPosition": 5,
        "resourceId": "com.example.homework3:id/logoutButton",
        "contentDescription": "",
        "text": "logout"
      },
      {
        "className": "androidx.constraintlayout.widget.ConstraintLayout",
        "recyclerViewChildPosition": -1,
        "adapterViewChildPosition": -1,
        "groupViewChildPosition": 0,
        "resourceId": "",
        "contentDescription": "",
        "text": ""
      },
      {
        "className": "androidx.fragment.app.FragmentContainerView",
        "recyclerViewChildPosition": -1,
        "adapterViewChildPosition": -1,
        "groupViewChildPosition": 0,
        "resourceId": "com.example.homework3:id/fragmentContainerView",
        "contentDescription": "",
        "text": ""
      }
    ]
  },
  {
    "eventType": "VIEW_CLICKED",
    "timestamp": 1661765738166,
    "replacementText": "Don\u0027t have an account? Register here.",
    "actionCode": -1,
    "delayTime": 0,
    "canScrollTo": false,
    "elementDescriptors": [
      {
        "className": "com.google.android.material.textview.MaterialTextView",
        "recyclerViewChildPosition": -1,
        "adapterViewChildPosition": -1,
        "groupViewChildPosition": 4,
        "resourceId": "com.example.homework3:id/tvRegisterHere",
        "contentDescription": "",
        "text": "Don\u0027t have an account? Register here."
      },
      {
        "className": "androidx.constraintlayout.widget.ConstraintLayout",
        "recyclerViewChildPosition": -1,
        "adapterViewChildPosition": -1,
        "groupViewChildPosition": 0,
        "resourceId": "",
        "contentDescription": "",
        "text": ""
      },
      {
        "className": "androidx.fragment.app.FragmentContainerView",
        "recyclerViewChildPosition": -1,
        "adapterViewChildPosition": -1,
        "groupViewChildPosition": 0,
        "resourceId": "com.example.homework3:id/fragmentContainerView",
        "contentDescription": "",
        "text": ""
      }
    ]
  }
]